hdl/crcd64_o8.v
`timescale 1ns / 1ps
module crcd64_o8 (
    input  [7:0] crc_in  ,//8'hFF
    input  [63:0] data_in,//input data to CRC
    output [7:0] crc_out
);
    assign crc_out[0] = crc_in[0] ^ crc_in[4] ^ crc_in[7] ^ data_in[0] ^ data_in[6] ^ data_in[7] ^
        data_in[8] ^ data_in[12] ^ data_in[14] ^ data_in[16] ^ data_in[18] ^ data_in[19] ^
        data_in[21] ^ data_in[23] ^ data_in[28] ^ data_in[30] ^ data_in[31] ^ data_in[34] ^
        data_in[35] ^ data_in[39] ^ data_in[40] ^ data_in[43] ^ data_in[45] ^ data_in[48] ^
        data_in[49] ^ data_in[50] ^ data_in[52] ^ data_in[53] ^ data_in[54] ^ data_in[56] ^
        data_in[60] ^ data_in[63];
    assign crc_out[1] = crc_in[0] ^ crc_in[1] ^ crc_in[4] ^ crc_in[5] ^ crc_in[7] ^ data_in[0] ^
        data_in[1] ^ data_in[6] ^ data_in[9] ^ data_in[12] ^ data_in[13] ^ data_in[14] ^
        data_in[15] ^ data_in[16] ^ data_in[17] ^ data_in[18] ^ data_in[20] ^ data_in[21] ^
        data_in[22] ^ data_in[23] ^ data_in[24] ^ data_in[28] ^ data_in[29] ^ data_in[30] ^
        data_in[32] ^ data_in[34] ^ data_in[36] ^ data_in[39] ^ data_in[41] ^ data_in[43] ^
        data_in[44] ^ data_in[45] ^ data_in[46] ^ data_in[48] ^ data_in[51] ^ data_in[52] ^
        data_in[55] ^ data_in[56] ^ data_in[57] ^ data_in[60] ^ data_in[61] ^ data_in[63];
    assign crc_out[2] = crc_in[1] ^ crc_in[2] ^ crc_in[4] ^ crc_in[5] ^ crc_in[6] ^ crc_in[7] ^
        data_in[0] ^ data_in[1] ^ data_in[2] ^ data_in[6] ^ data_in[8] ^ data_in[10] ^
        data_in[12] ^ data_in[13] ^ data_in[15] ^ data_in[17] ^ data_in[22] ^ data_in[24] ^
        data_in[25] ^ data_in[28] ^ data_in[29] ^ data_in[33] ^ data_in[34] ^ data_in[37] ^
        data_in[39] ^ data_in[42] ^ data_in[43] ^ data_in[44] ^ data_in[46] ^ data_in[47] ^
        data_in[48] ^ data_in[50] ^ data_in[54] ^ data_in[57] ^ data_in[58] ^ data_in[60] ^
        data_in[61] ^ data_in[62] ^ data_in[63];
    assign crc_out[3] = crc_in[2] ^ crc_in[3] ^ crc_in[5] ^ crc_in[6] ^ crc_in[7] ^ data_in[1] ^
        data_in[2] ^ data_in[3] ^ data_in[7] ^ data_in[9] ^ data_in[11] ^ data_in[13] ^
        data_in[14] ^ data_in[16] ^ data_in[18] ^ data_in[23] ^ data_in[25] ^ data_in[26] ^
        data_in[29] ^ data_in[30] ^ data_in[34] ^ data_in[35] ^ data_in[38] ^ data_in[40] ^
        data_in[43] ^ data_in[44] ^ data_in[45] ^ data_in[47] ^ data_in[48] ^ data_in[49] ^
        data_in[51] ^ data_in[55] ^ data_in[58] ^ data_in[59] ^
        data_in[61] ^ data_in[62] ^ data_in[63];
    assign crc_out[4] = crc_in[0] ^ crc_in[3] ^ crc_in[4] ^ crc_in[6] ^ crc_in[7] ^ data_in[2] ^
        data_in[3] ^ data_in[4] ^ data_in[8] ^ data_in[10] ^ data_in[12] ^ data_in[14] ^
        data_in[15] ^ data_in[17] ^ data_in[19] ^ data_in[24] ^ data_in[26] ^ data_in[27] ^
        data_in[30] ^ data_in[31] ^ data_in[35] ^ data_in[36] ^ data_in[39] ^ data_in[41] ^
        data_in[44] ^ data_in[45] ^ data_in[46] ^ data_in[48] ^ data_in[49] ^ data_in[50] ^
        data_in[52] ^ data_in[56] ^ data_in[59] ^ data_in[60] ^ data_in[62] ^ data_in[63];
    assign crc_out[5] = crc_in[1] ^ crc_in[4] ^ crc_in[5] ^ crc_in[7] ^ data_in[3] ^ data_in[4] ^
        data_in[5] ^ data_in[9] ^ data_in[11] ^ data_in[13] ^ data_in[15] ^ data_in[16] ^
        data_in[18] ^ data_in[20] ^ data_in[25] ^ data_in[27] ^ data_in[28] ^ data_in[31] ^
        data_in[32] ^ data_in[36] ^ data_in[37] ^ data_in[40] ^ data_in[42] ^ data_in[45] ^
        data_in[46] ^ data_in[47] ^ data_in[49] ^ data_in[50] ^ data_in[51] ^ data_in[53] ^
        data_in[57] ^ data_in[60] ^ data_in[61] ^ data_in[63];
    assign crc_out[6] = crc_in[2] ^ crc_in[5] ^ crc_in[6] ^ data_in[4] ^ data_in[5] ^ data_in[6] ^
        data_in[10] ^ data_in[12] ^ data_in[14] ^ data_in[16] ^ data_in[17] ^ data_in[19] ^
        data_in[21] ^ data_in[26] ^ data_in[28] ^ data_in[29] ^ data_in[32] ^ data_in[33] ^
        data_in[37] ^ data_in[38] ^ data_in[41] ^ data_in[43] ^ data_in[46] ^ data_in[47] ^
        data_in[48] ^ data_in[50] ^ data_in[51] ^ data_in[52] ^ data_in[54] ^ data_in[58] ^
        data_in[61] ^ data_in[62];
    assign crc_out[7] = crc_in[3] ^ crc_in[6] ^ crc_in[7] ^ data_in[5] ^ data_in[6] ^ data_in[7] ^
        data_in[11] ^ data_in[13] ^ data_in[15] ^ data_in[17] ^ data_in[18] ^ data_in[20] ^
        data_in[22] ^ data_in[27] ^ data_in[29] ^ data_in[30] ^ data_in[33] ^ data_in[34] ^
        data_in[38] ^ data_in[39] ^ data_in[42] ^ data_in[44] ^ data_in[47] ^ data_in[48] ^
        data_in[49] ^ data_in[51] ^ data_in[52] ^ data_in[53] ^ data_in[55] ^ data_in[59] ^
        data_in[62] ^ data_in[63];

endmodule

hdl/lin_resp.v
`timescale 1ns / 1ps

module lin_resp(
    input  wire        sys_clk,          // system clock
    input  wire        rstn,             // active-low reset
    input  wire        lin_busy,         // commander busy
    input  wire        comm_tx_done,     // TX complete from commander
    input  wire [33:0] frame_header_out, // header from commander
    input  wire [63:0] data,             // input data to responder
    output reg  [89:0] response_out,     // response from responder
    output wire [7:0]  checksum,         // checksum/CRC out
    output reg         sdo_resp,         // serial data out from responder
    output reg         resp_tx_done,     // TX complete from responder
    output reg         resp_busy         // responder busy
);

    // FSM states
    localparam IDLE     = 3'd0;
    localparam START    = 3'd1;
    localparam DATA     = 3'd2;
    localparam STOP     = 3'd3;
    localparam CHK_START= 3'd4;
    localparam CHECKSUM = 3'd5;
    localparam CHK_STOP = 3'd6;

    reg [2:0] state;
    reg [63:0] data_reg;
    reg [7:0] checksum_reg;
    reg [3:0] bit_count;
    reg [3:0] byte_count;

    wire [7:0] sync_data;
    wire [7:0] crc_in;

    assign sync_data = frame_header_out[19:12]; // sync byte = 0x55
    assign crc_in = 8'hFF;

    // CRC instantiation
    crcd64_o8 CRCD64_O8 (
        .crc_in(crc_in),
        .data_in(data),
        .crc_out(checksum)
    );

    // FSM for responder
    always @(posedge sys_clk or negedge rstn) begin
        if (!rstn) begin
            response_out   <= 90'd0;
            sdo_resp       <= 1'b1;   // line idle high
            resp_busy      <= 1'b0;
            resp_tx_done   <= 1'b0;
            state          <= IDLE;
            data_reg       <= 64'd0;
            checksum_reg   <= 8'd0;
            bit_count      <= 4'd0;
            byte_count     <= 4'd0;
        end else begin
            case(state)
                IDLE: begin
                    response_out   <= 90'd0;
                    resp_tx_done   <= 1'b0;
                    resp_busy      <= 1'b0;
                    bit_count      <= 4'd0;
                    byte_count     <= 4'd0;
                    if (!lin_busy && comm_tx_done && sync_data == 8'h55) begin
                        data_reg     <= data;
                        checksum_reg <= checksum;
                        resp_busy    <= 1'b1;
                        sdo_resp     <= 1'b0; // start bit
                        state        <= START;
                    end
                end

                // start bit already set
                START: begin
                    response_out <= {response_out[88:0], sdo_resp};
                    sdo_resp     <= data_reg[0];   // first data bit
                    data_reg     <= {1'b0, data_reg[63:1]};
                    bit_count    <= 4'd1;
                    state        <= DATA;
                end

                DATA: begin
                    response_out <= {response_out[88:0], sdo_resp};
                    if (bit_count < 8) begin
                        sdo_resp  <= data_reg[0];
                        data_reg  <= {1'b0, data_reg[63:1]};
                        bit_count <= bit_count + 1;
                    end else begin
                        sdo_resp  <= 1'b1; // stop bit
                        bit_count <= 4'd0;
                        state     <= STOP;
                    end
                end

                STOP: begin
                    response_out <= {response_out[88:0], sdo_resp};
                    if (byte_count < 7) begin
                        byte_count <= byte_count + 1;
                        sdo_resp   <= 1'b0; // next start bit
                        state      <= START;
                    end else begin
                        sdo_resp   <= 1'b0; // checksum start
                        state      <= CHK_START;
                    end
                end

                CHK_START: begin
                    response_out <= {response_out[88:0], sdo_resp};
                    sdo_resp     <= checksum_reg[0];
                    checksum_reg <= {1'b0, checksum_reg[7:1]};
                    bit_count    <= 4'd1;
                    state        <= CHECKSUM;
                end

                CHECKSUM: begin
                    response_out <= {response_out[88:0], sdo_resp};
                    if (bit_count < 8) begin
                        sdo_resp     <= checksum_reg[0];
                        checksum_reg <= {1'b0, checksum_reg[7:1]};
                        bit_count    <= bit_count + 1;
                    end else begin
                        sdo_resp  <= 1'b1; // checksum stop bit
                        state     <= CHK_STOP;
                    end
                end

                CHK_STOP: begin
                    response_out <= {response_out[88:0], sdo_resp};
                    resp_tx_done <= 1'b1;
                    resp_busy    <= 1'b0;
                    state        <= IDLE;
                end

                default: state <= IDLE;
            endcase
        end
    end
endmodule

hdl/lin_comm.v
`timescale 1ns / 1ps

module lin_comm(
    input  wire        sys_clk,        // system clock
    input  wire        rstn,           // reset (active low)
    input  wire        start,          // start commander
    input  wire [5:0]  pid,            // id or address
    input  wire        inter_tx_delay, // inter transmission delay
    input  wire        resp_busy,      // responder busy
    output reg         sdo_comm,       // serial data out
    output wire        lin_busy,       // commander busy
    output reg         comm_tx_done,   // tx complete from commander
    output reg [33:0]  frame_header_out // frame header
    );

    // counters / registers
    reg [3:0] break_count;     // count for break field (needs to count >=13)
    reg [3:0] sync_count;      // count for sync field (0..9)
    reg [5:0] pid_adrs_reg;    // PID register (shifted out LSB first)
    reg [3:0] pid_count;       // count for PID (start + 6 id bits)
    reg [1:0] parity_count;    // count for parity (0..2)
    reg parity0;               // parity bit 0
    reg parity1;               // parity bit 1
    reg [33:0] frame_header;   // frame header register (34 bits)

    // temporary / helper
    reg next_sdo;              // the bit we intend to drive this cycle
    reg append_bit;            // whether to capture next_sdo into frame_header this cycle

    // SYNC pattern (LSB first sequence for 0x55 -> bits transmitted: 1,0,1,0,1,0,1,0 )
    localparam [7:0] SYNC_PATTERN = 8'b01010101; // bit0 = first transmitted data bit (LSB-first)

    // FSM states as localparams
    localparam IDLE       = 3'd0;
    localparam SYNC_BREAK = 3'd1;
    localparam SYNC_FIELD = 3'd2;
    localparam PID_STATE  = 3'd3;
    localparam PARITY     = 3'd4;
    localparam WAIT       = 3'd6;

    reg [2:0] state; // current state

    // Main synchronous FSM
    // Approach: compute next_sdo and append_bit (blocking style within this clock),
    // then update sdo_comm and frame_header using next_sdo so the captured header aligns
    // exactly with the bits driven on sdo_comm (no one-cycle offset).
    always @(posedge sys_clk or negedge rstn) begin
        if (!rstn) begin
            // reset all sequential state
            sdo_comm       <= 1'b0;
            break_count    <= 4'd0;
            sync_count     <= 4'd0;
            pid_count      <= 4'd0;
            pid_adrs_reg   <= 6'd0;
            parity_count   <= 2'd0;
            parity0        <= 1'b0;
            parity1        <= 1'b0;
            comm_tx_done   <= 1'b0;
            frame_header   <= 34'd0;
            state          <= IDLE;
            next_sdo       <= 1'b0;
            append_bit     <= 1'b0;
        end else begin
            // Default behaviors for the combinational decisions in this clock
            // Use blocking assignments for next_sdo/append_bit so these are used
            // when updating frame_header and sdo_comm below.
            next_sdo   = 1'b1;   // idle-high by default (can be overridden)
            append_bit = 1'b0;   // do not append unless explicitly requested

            // Default: keep most sequential regs the same unless updated using non-blocking below
            case (state)
                IDLE: begin
                    // In IDLE we latch PID and wait for start condition
                    // Keep outputs/reset counters as needed
                    // Drive bus idle value (choose 1 or 0 depending on bus convention)
                    next_sdo = 1'b1; // idle-high
                    append_bit = 1'b0;

                    // make sure comm_tx_done is cleared when entering IDLE
                    comm_tx_done <= 1'b0;
                    break_count  <= 4'd0;
                    sync_count   <= 4'd0;
                    pid_count    <= 4'd0;
                    parity_count <= 2'd0;
                    pid_adrs_reg <= pid; // latch PID value

                    if (start && !inter_tx_delay && !resp_busy) begin
                        state <= SYNC_BREAK;
                    end else begin
                        state <= IDLE;
                    end
                end

                // SYNC_BREAK: drive >=13 low bits, then one delimiter high
                SYNC_BREAK: begin
                    if (break_count < 13) begin
                        next_sdo = 1'b0;    // drive break low
                        append_bit = 1'b1;  // capture this bit into header
                        break_count <= break_count + 1;
                        state <= SYNC_BREAK;
                    end else begin
                        next_sdo = 1'b1;    // delimiter high
                        append_bit = 1'b1;
                        break_count <= 4'd0;
                        state <= SYNC_FIELD;
                    end
                end

                // SYNC_FIELD: start(0), 8-data bits (0x55 LSB-first), stop(1)
                SYNC_FIELD: begin
                    if (sync_count == 0) begin
                        next_sdo = 1'b0;    // start bit
                        append_bit = 1'b1;
                        sync_count <= sync_count + 1;
                        state <= SYNC_FIELD;
                    end else if (sync_count >= 1 && sync_count <= 8) begin
                        next_sdo = SYNC_PATTERN[sync_count-1]; // data bits LSB-first
                        append_bit = 1'b1;
                        sync_count <= sync_count + 1;
                        state <= SYNC_FIELD;
                    end else begin
                        // sync_count == 9 -> stop bit
                        next_sdo = 1'b1;    // stop bit
                        append_bit = 1'b1;
                        sync_count <= 4'd0;
                        state <= PID_STATE;
                    end
                end

                // PID_STATE: start(0) + 6 ID bits (LSB-first)
                PID_STATE: begin
                    if (pid_count == 0) begin
                        next_sdo = 1'b0;    // PID start bit
                        append_bit = 1'b1;
                        pid_count <= pid_count + 1;
                        state <= PID_STATE;
                    end else if (pid_count >= 1 && pid_count <= 6) begin
                        // send LSB-first ID bits and shift the register
                        next_sdo = pid_adrs_reg[0];
                        append_bit = 1'b1;
                        pid_adrs_reg <= {1'b0, pid_adrs_reg[5:1]};
                        pid_count <= pid_count + 1;
                        state <= PID_STATE;
                    end else begin
                        // finished sending ID bits -> compute parity and go to PARITY
                        parity0 <= pid[0] ^ pid[1] ^ pid[2] ^ pid[4];
                        parity1 <= ~(pid[1] ^ pid[3] ^ pid[4] ^ pid[5]);
                        pid_count <= 4'd0;
                        parity_count <= 2'd0;
                        // do NOT append here; parity state will drive the parity bits
                        state <= PARITY;
                    end
                end

                // PARITY: send P0, P1, then a stop bit and finish (move to WAIT)
                PARITY: begin
                    if (parity_count == 0) begin
                        next_sdo = parity0;
                        append_bit = 1'b1;
                        parity_count <= parity_count + 1;
                        state <= PARITY;
                    end else if (parity_count == 1) begin
                        next_sdo = parity1;
                        append_bit = 1'b1;
                        parity_count <= parity_count + 1;
                        state <= PARITY;
                    end else begin
                        // After two parity bits, drive the PID stop bit (1), append it,
                        // assert comm_tx_done and move to WAIT in the same cycle so
                        // the frame_header contains exactly the complete header.
                        next_sdo = 1'b1;    // PID stop bit
                        append_bit = 1'b1;
                        parity_count <= 2'd0;
                        comm_tx_done <= 1'b1; // indicate header is complete (available)
                        state <= WAIT;
                    end
                end

                // WAIT: wait for responder to become not busy, then go to IDLE
                WAIT: begin
                    next_sdo = 1'b1; // idle level
                    append_bit = 1'b0;
                    if (resp_busy)
                        state <= WAIT;
                    else
                        state <= IDLE;
                end

                default: begin
                    next_sdo = 1'b1;
                    append_bit = 1'b0;
                    state <= IDLE;
                end
            endcase

            // Update the driven line and optionally capture it into the header
            // Use non-blocking updates so sequential behavior is correct.
            sdo_comm <= next_sdo;
            if (append_bit)
                frame_header <= {frame_header[32:0], next_sdo};
            else
                frame_header <= frame_header;
        end
    end

    assign lin_busy = (state == SYNC_BREAK) || (state == SYNC_FIELD) || (state == PID_STATE) || (state == PARITY);

    // Provide the captured header externally only when comm_tx_done is asserted.
    always @(*) frame_header_out = comm_tx_done ? frame_header : 34'd0;

endmodule

hdl/lin_top.v
`timescale 1ns / 1ps

module lin_top(
    input  wire        sys_clk,       // system clock
    input  wire        rstn,          // reset
    input  wire [5:0]  pid,           // id or address
    input  wire [63:0] data,          // input data to responder
    output wire        sdo_comm,      // serial data out from commander
    output wire        sdo_resp,      // serial data out from responder
    output wire [33:0] frame_header_out, // header from commander
    output wire [89:0] response_out,     // response from responder
    output wire        comm_tx_done,  // tx complete from commander
    output wire        resp_tx_done    // tx complete from responder
    );

    reg         inter_tx_delay;    // inter transmission delay
    reg [4:0]   delay_count;       // inter transmission delay count
    reg         start;             // start commander
    wire        resp_busy;         // responder busy
    wire        lin_busy;          // commander busy
    reg [7:0]   checksum;          // responder checksum
    wire [123:0] frame_out;        // total frame from commander and responder

    // LIN Commander instantiation
    lin_comm LIN_COMM(
        .sys_clk        (sys_clk       ),
        .rstn           (rstn          ),
        .start          (start         ),
        .pid            (pid           ),
        .inter_tx_delay (inter_tx_delay),
        .resp_busy      (resp_busy     ),
        .sdo_comm       (sdo_comm      ),
        .lin_busy       (lin_busy      ),
        .comm_tx_done   (comm_tx_done  ),
        .frame_header_out (frame_header_out)
    );

    // LIN Responder instantiation
    lin_resp LIN_RESP(
        .sys_clk          (sys_clk         ),
        .rstn             (rstn            ),
        .lin_busy         (lin_busy        ),
        .comm_tx_done     (comm_tx_done    ),
        .frame_header_out (frame_header_out),
        .data             (data            ),
        .response_out     (response_out    ),
        .checksum         (checksum        ),
        .sdo_resp         (sdo_resp        ),
        .resp_tx_done     (resp_tx_done    ),
        .resp_busy        (resp_busy       )
    );

    // FSM states as localparams
    localparam IDLE  = 0;
    localparam DELAY = 1;
    reg state;

    assign frame_out = resp_tx_done ? {frame_header_out, response_out} : 0; // frame output after responder tx done

    // start condition for commander
    always @(posedge sys_clk or negedge rstn) begin
        if (!rstn) begin
            start <= 0;
        end else if (!resp_tx_done && !resp_busy) begin
            start <= 1;
        end else begin
            start <= 0;
        end
    end

    // delay generation after responder tx done
    always @(posedge sys_clk or negedge rstn) begin
        if (!rstn) begin
            inter_tx_delay <= 0;
            delay_count <= 0;
            state <= IDLE;
        end else begin
            case(state)
                IDLE: begin
                    inter_tx_delay <= 0;
                    delay_count <= 0;
                    if (resp_tx_done)
                        state <= DELAY;
                    else
                        state <= IDLE;
                end
                DELAY: begin
                    if (delay_count < 20) begin
                        delay_count <= delay_count + 1;
                        inter_tx_delay <= 1; // tx delay for 20 ns
                        state <= DELAY;
                    end else begin
                        delay_count <= 0;
                        inter_tx_delay <= 0;
                        state <= IDLE;
                    end
                end
                default: state <= IDLE;
            endcase
        end
    end

endmodule

hdl/lin_top_wrapper.v
`timescale 1ns / 1ps

module lin_top_wrapper;

    // Clock and reset
    reg         sys_clk;
    reg         rstn;

    // Inputs to DUT
    reg  [5:0]  pid;
    reg  [63:0] data;

    // Outputs from DUT
    wire        sdo_comm;
    wire        sdo_resp;
    wire [33:0] frame_header_out;
    wire [89:0] response_out;
    wire        comm_tx_done;
    wire        resp_tx_done;

    // Instantiate DUT
    lin_top DUT (
        .sys_clk        (sys_clk),
        .rstn           (rstn),
        .pid            (pid),
        .data           (data),
        .sdo_comm       (sdo_comm),
        .sdo_resp       (sdo_resp),
        .frame_header_out(frame_header_out),
        .response_out   (response_out),
        .comm_tx_done   (comm_tx_done),
        .resp_tx_done   (resp_tx_done)
    );

    initial begin
        $dumpfile("waves.vcd");
        $dumpvars;
        sys_clk=0;
        forever begin
                #5 sys_clk=~sys_clk;
        end
    end
endmodule

tests/waves.vcd
$date
	Tue Sep  9 13:38:22 2025
$end
$version
	Icarus Verilog
$end
$timescale
	1ps
$end
$scope module lin_top_wrapper $end
$var wire 1 ! sdo_resp $end
$var wire 1 " sdo_comm $end
$var wire 90 # response_out [89:0] $end
$var wire 1 $ resp_tx_done $end
$var wire 34 % frame_header_out [33:0] $end
$var wire 1 & comm_tx_done $end
$var reg 64 ' data [63:0] $end
$var reg 6 ( pid [5:0] $end
$var reg 1 ) rstn $end
$var reg 1 * sys_clk $end
$scope module DUT $end
$var wire 64 + data [63:0] $end
$var wire 6 , pid [5:0] $end
$var wire 1 ) rstn $end
$var wire 1 * sys_clk $end
$var wire 1 ! sdo_resp $end
$var wire 1 " sdo_comm $end
$var wire 90 - response_out [89:0] $end
$var wire 1 $ resp_tx_done $end
$var wire 1 . resp_busy $end
$var wire 1 / lin_busy $end
$var wire 124 0 frame_out [123:0] $end
$var wire 34 1 frame_header_out [33:0] $end
$var wire 1 & comm_tx_done $end
$var wire 8 2 checksum [7:0] $end
$var parameter 32 3 DELAY $end
$var parameter 32 4 IDLE $end
$var reg 5 5 delay_count [4:0] $end
$var reg 1 6 inter_tx_delay $end
$var reg 1 7 start $end
$var reg 1 8 state $end
$scope module LIN_COMM $end
$var wire 1 6 inter_tx_delay $end
$var wire 1 / lin_busy $end
$var wire 6 9 pid [5:0] $end
$var wire 1 ) rstn $end
$var wire 1 7 start $end
$var wire 1 * sys_clk $end
$var wire 1 . resp_busy $end
$var parameter 3 : IDLE $end
$var parameter 3 ; PARITY $end
$var parameter 3 < PID_STATE $end
$var parameter 3 = SYNC_BREAK $end
$var parameter 3 > SYNC_FIELD $end
$var parameter 8 ? SYNC_PATTERN $end
$var parameter 3 @ WAIT $end
$var reg 1 A append_bit $end
$var reg 4 B break_count [3:0] $end
$var reg 1 & comm_tx_done $end
$var reg 34 C frame_header [33:0] $end
$var reg 34 D frame_header_out [33:0] $end
$var reg 1 E next_sdo $end
$var reg 1 F parity0 $end
$var reg 1 G parity1 $end
$var reg 2 H parity_count [1:0] $end
$var reg 6 I pid_adrs_reg [5:0] $end
$var reg 4 J pid_count [3:0] $end
$var reg 1 " sdo_comm $end
$var reg 3 K state [2:0] $end
$var reg 4 L sync_count [3:0] $end
$upscope $end
$scope module LIN_RESP $end
$var wire 1 & comm_tx_done $end
$var wire 8 M crc_in [7:0] $end
$var wire 64 N data [63:0] $end
$var wire 34 O frame_header_out [33:0] $end
$var wire 1 / lin_busy $end
$var wire 1 ) rstn $end
$var wire 1 * sys_clk $end
$var wire 8 P sync_data [7:0] $end
$var wire 8 Q checksum [7:0] $end
$var parameter 3 R CHECKSUM $end
$var parameter 3 S CHK_START $end
$var parameter 3 T CHK_STOP $end
$var parameter 3 U DATA $end
$var parameter 3 V IDLE $end
$var parameter 3 W START $end
$var parameter 3 X STOP $end
$var reg 4 Y bit_count [3:0] $end
$var reg 4 Z byte_count [3:0] $end
$var reg 8 [ checksum_reg [7:0] $end
$var reg 64 \ data_reg [63:0] $end
$var reg 1 . resp_busy $end
$var reg 1 $ resp_tx_done $end
$var reg 90 ] response_out [89:0] $end
$var reg 1 ! sdo_resp $end
$var reg 3 ^ state [2:0] $end
$scope module CRCD64_O8 $end
$var wire 8 _ crc_in [7:0] $end
$var wire 64 ` data_in [63:0] $end
$var wire 8 a crc_out [7:0] $end
$upscope $end
$upscope $end
$upscope $end
$upscope $end
$enddefinitions $end
$comment Show the parameter values. $end
$dumpall
b11 X
b1 W
b0 V
b10 U
b110 T
b100 S
b101 R
b110 @
b1010101 ?
b10 >
b1 =
b11 <
b100 ;
b0 :
b0 4
b1 3
$end
#0
$dumpvars
bx a
bx `
b11111111 _
bx ^
bx ]
bx \
bx [
bx Z
bx Y
bx Q
bx P
bx O
bx N
b11111111 M
bx L
bx K
bx J
bx I
bx H
xG
xF
xE
bx D
bx C
bx B
xA
bx 9
x8
x7
x6
bx 5
bx 2
bx 1
bx 0
x/
x.
bx -
bx ,
bx +
0*
1)
bx (
bx '
x&
bx %
x$
bx #
x"
x!
$end
#1000
0/
b0 P
b0 %
b0 1
b0 D
b0 O
b0 0
0A
0E
b0 K
b0 C
0&
0G
0F
b0 H
b0 I
b0 J
b0 L
b0 B
0"
b0 Z
b0 Y
b0 [
b0 \
b0 ^
0$
0.
1!
b0 #
b0 -
b0 ]
07
08
b0 5
06
0)
#5000
b1110101 2
b1110101 Q
b1110101 a
b10110001111000111011001110001011101111 '
b10110001111000111011001110001011101111 +
b10110001111000111011001110001011101111 N
b10110001111000111011001110001011101111 `
b1100 (
b1100 ,
b1100 9
1)
1*
#10000
0*
#15000
1"
b1100 I
17
1E
1*
#20000
0*
#25000
1/
b1 K
1*
#30000
0*
#35000
0"
b1 B
1A
0E
1*
#40000
0*
#45000
b10 B
1A
0E
1*
#50000
0*
#55000
b11 B
1A
0E
1*
#60000
0*
#65000
b100 B
1A
0E
1*
#70000
0*
#75000
b101 B
1A
0E
1*
#80000
0*
#85000
b110 B
1A
0E
1*
#90000
0*
#95000
b111 B
1A
0E
1*
#100000
0*
#105000
b1000 B
1A
0E
1*
#110000
0*
#115000
b1001 B
1A
0E
1*
#120000
0*
#125000
b1010 B
1A
0E
1*
#130000
0*
#135000
b1011 B
1A
0E
1*
#140000
0*
#145000
b1100 B
1A
0E
1*
#150000
0*
#155000
b1101 B
1A
0E
1*
#160000
0*
#165000
b1 C
1"
b10 K
b0 B
1A
1E
1*
#170000
0*
#175000
b10 C
0"
b1 L
0E
1A
1*
#180000
0*
#185000
b101 C
1"
b10 L
1A
1E
1*
#190000
0*
#195000
b1010 C
0"
b11 L
0E
1A
1*
#200000
0*
#205000
b10101 C
1"
b100 L
1A
1E
1*
#210000
0*
#215000
b101010 C
0"
b101 L
0E
1A
1*
#220000
0*
#225000
b1010101 C
1"
b110 L
1A
1E
1*
#230000
0*
#235000
b10101010 C
0"
b111 L
0E
1A
1*
#240000
0*
#245000
b101010101 C
1"
b1000 L
1A
1E
1*
#250000
0*
#255000
b1010101010 C
0"
b1001 L
0E
1A
1*
#260000
0*
#265000
b10101010101 C
1"
b11 K
b0 L
1A
1E
1*
#270000
0*
#275000
b101010101010 C
0"
b1 J
0E
1A
1*
#280000
0*
#285000
b1010101010100 C
b10 J
b110 I
1A
0E
1*
#290000
0*
#295000
b10101010101000 C
b11 J
b11 I
1A
0E
1*
#300000
0*
#305000
b101010101010001 C
1"
b100 J
b1 I
1A
1E
1*
#310000
0*
#315000
b1010101010100011 C
b101 J
b0 I
1A
1*
#320000
0*
#325000
b10101010101000110 C
0"
b110 J
0E
1A
1*
#330000
0*
#335000
b101010101010001100 C
b111 J
1A
0E
1*
#340000
0*
#345000
1"
b100 K
b0 J
1F
0A
1E
1*
#350000
0*
#355000
b1010101010100011001 C
b1 H
1A
1*
#360000
0*
#365000
b10101010101000110010 C
0"
b10 H
0E
1A
1*
#370000
0*
#375000
b1010101 P
0/
b101010101010001100101 %
b101010101010001100101 1
b101010101010001100101 D
b101010101010001100101 O
b101010101010001100101 C
1"
b110 K
1&
b0 H
1A
1E
1*
#380000
0*
#385000
b1 ^
0!
1.
b1110101 [
b10110001111000111011001110001011101111 \
b0 K
0A
1*
#390000
0*
#395000
b0 P
b0 %
b0 1
b0 D
b0 O
b1100 I
0&
b10 ^
b1 Y
b1011000111100011101100111000101110111 \
1!
07
1*
#400000
0*
#405000
b10 Y
b101100011110001110110011100010111011 \
b1 #
b1 -
b1 ]
1*
#410000
0*
#415000
b11 Y
b10110001111000111011001110001011101 \
b11 #
b11 -
b11 ]
1*
#420000
0*
#425000
b100 Y
b1011000111100011101100111000101110 \
b111 #
b111 -
b111 ]
1*
#430000
0*
#435000
b101 Y
b101100011110001110110011100010111 \
0!
b1111 #
b1111 -
b1111 ]
1*
#440000
0*
#445000
b110 Y
b10110001111000111011001110001011 \
1!
b11110 #
b11110 -
b11110 ]
1*
#450000
0*
#455000
b111 Y
b1011000111100011101100111000101 \
b111101 #
b111101 -
b111101 ]
1*
#460000
0*
#465000
b1000 Y
b101100011110001110110011100010 \
b1111011 #
b1111011 -
b1111011 ]
1*
#470000
0*
#475000
b11 ^
b0 Y
b11110111 #
b11110111 -
b11110111 ]
1*
#480000
0*
#485000
b1 ^
0!
b1 Z
b111101111 #
b111101111 -
b111101111 ]
1*
#490000
0*
#495000
b10 ^
b1 Y
b10110001111000111011001110001 \
b1111011110 #
b1111011110 -
b1111011110 ]
1*
#500000
0*
#505000
b10 Y
b1011000111100011101100111000 \
1!
b11110111100 #
b11110111100 -
b11110111100 ]
1*
#510000
0*
#515000
b11 Y
b101100011110001110110011100 \
0!
b111101111001 #
b111101111001 -
b111101111001 ]
1*
#520000
0*
#525000
b100 Y
b10110001111000111011001110 \
b1111011110010 #
b1111011110010 -
b1111011110010 ]
1*
#530000
0*
#535000
b101 Y
b1011000111100011101100111 \
b11110111100100 #
b11110111100100 -
b11110111100100 ]
1*
#540000
0*
#545000
b110 Y
b101100011110001110110011 \
1!
b111101111001000 #
b111101111001000 -
b111101111001000 ]
1*
#550000
0*
#555000
b111 Y
b10110001111000111011001 \
b1111011110010001 #
b1111011110010001 -
b1111011110010001 ]
1*
#560000
0*
#565000
b1000 Y
b1011000111100011101100 \
b11110111100100011 #
b11110111100100011 -
b11110111100100011 ]
1*
#570000
0*
#575000
b11 ^
b0 Y
b111101111001000111 #
b111101111001000111 -
b111101111001000111 ]
1*
#580000
0*
#585000
b1 ^
0!
b10 Z
b1111011110010001111 #
b1111011110010001111 -
b1111011110010001111 ]
1*
#590000
0*
#595000
b10 ^
b1 Y
b101100011110001110110 \
b11110111100100011110 #
b11110111100100011110 -
b11110111100100011110 ]
1*
#600000
0*
#605000
b10 Y
b10110001111000111011 \
b111101111001000111100 #
b111101111001000111100 -
b111101111001000111100 ]
1*
#610000
0*
#615000
b11 Y
b1011000111100011101 \
1!
b1111011110010001111000 #
b1111011110010001111000 -
b1111011110010001111000 ]
1*
#620000
0*
#625000
b100 Y
b101100011110001110 \
b11110111100100011110001 #
b11110111100100011110001 -
b11110111100100011110001 ]
1*
#630000
0*
#635000
b101 Y
b10110001111000111 \
0!
b111101111001000111100011 #
b111101111001000111100011 -
b111101111001000111100011 ]
1*
#640000
0*
#645000
b110 Y
b1011000111100011 \
1!
b1111011110010001111000110 #
b1111011110010001111000110 -
b1111011110010001111000110 ]
1*
#650000
0*
